yascheduler/__init__.py
yascheduler/aiida_plugin.py
yascheduler/client.py
yascheduler/compat.py
yascheduler/daemon_systemd.py
yascheduler/daemon_sysv.py
yascheduler/db.py
yascheduler/queue.py
yascheduler/scheduler.py
yascheduler/time.py
yascheduler/utils.py
yascheduler/variables.py
yascheduler/clouds/__init__.py
yascheduler/clouds/adapters.py
yascheduler/clouds/az.py
yascheduler/clouds/cloud_api.py
yascheduler/clouds/cloud_api_manager.py
yascheduler/clouds/hetzner.py
yascheduler/clouds/protocols.py
yascheduler/clouds/upcloud.py
yascheduler/clouds/utils.py
yascheduler/config/__init__.py
yascheduler/config/cloud.py
yascheduler/config/config.py
yascheduler/config/db.py
yascheduler/config/engine.py
yascheduler/config/engine_repository.py
yascheduler/config/local.py
yascheduler/config/remote.py
yascheduler/config/utils.py
yascheduler/data/schema.sql
yascheduler/data/yascheduler.conf
yascheduler/data/yascheduler.service
yascheduler/data/yascheduler.sh
yascheduler/remote_machine/__init__.py
yascheduler/remote_machine/adapters.py
yascheduler/remote_machine/checks.py
yascheduler/remote_machine/common.py
yascheduler/remote_machine/exc.py
yascheduler/remote_machine/linux_methods.py
yascheduler/remote_machine/protocol.py
yascheduler/remote_machine/remote_machine.py
yascheduler/remote_machine/remote_machine_repository.py
yascheduler/remote_machine/windows_methods.py
yascheduler-1.5.0.dist-info/licenses/LICENSE
yascheduler-1.5.0.dist-info/METADATA
yascheduler-1.5.0.dist-info/WHEEL
yascheduler-1.5.0.dist-info/entry_points.txt
yascheduler-1.5.0.dist-info/top_level.txt
yascheduler-1.5.0.dist-info/RECORD
