Metadata-Version: 2.4
Name: yascheduler
Version: 1.5.0
Summary: Yet another computing scheduler and cloud orchestration engine
Author-email: Sergei Korolev <knopki@duck.com>, Andrey Sobolev <as@tilde.pro>, Evgeny Blokhin <eb@tilde.pro>
License-Expression: MIT
Project-URL: Home, https://github.com/tilde-lab/yascheduler
Project-URL: Changelog, https://github.com/tilde-lab/yascheduler/blob/master/CHANGELOG.md
Project-URL: Issues, https://github.com/tilde-lab/yascheduler/issues
Project-URL: Source, https://github.com/tilde-lab/yascheduler
Classifier: Development Status :: 4 - Beta
Classifier: Intended Audience :: Science/Research
Classifier: Topic :: Scientific/Engineering :: Chemistry
Classifier: Topic :: Scientific/Engineering :: Physics
Classifier: Topic :: Scientific/Engineering :: Information Analysis
Classifier: Topic :: Software Development :: Libraries :: Python Modules
Classifier: Programming Language :: Python :: 3
Classifier: Programming Language :: Python :: 3.9
Classifier: Programming Language :: Python :: 3.10
Classifier: Programming Language :: Python :: 3.11
Classifier: Programming Language :: Python :: 3.12
Classifier: Programming Language :: Python :: 3.13
Classifier: Framework :: AiiDA
Requires-Python: >=3.9
License-File: LICENSE
Requires-Dist: aiohttp~=3.8
Requires-Dist: asyncssh~=2.11
Requires-Dist: asyncstdlib~=3.10
Requires-Dist: attrs>=22.2.0
Requires-Dist: backoff~=2.1.2
Requires-Dist: pg8000~=1.19
Requires-Dist: python-daemon~=2.3
Requires-Dist: typing-extensions>=4.2.0; python_version < "3.11"
Provides-Extra: azure
Requires-Dist: azure-identity~=1.10.0; extra == "azure"
Requires-Dist: azure-mgmt-compute~=27.2.0; extra == "azure"
Requires-Dist: azure-mgmt-network~=20.0.0; extra == "azure"
Provides-Extra: hetzner
Requires-Dist: hcloud~=2.0; extra == "hetzner"
Provides-Extra: upcloud
Requires-Dist: upcloud_api~=2.0; extra == "upcloud"
Provides-Extra: dev
Requires-Dist: build; extra == "dev"
Requires-Dist: commitizen; extra == "dev"
Requires-Dist: pyright; extra == "dev"
Requires-Dist: pyupgrade; extra == "dev"
Requires-Dist: ruff; extra == "dev"
Requires-Dist: twine; extra == "dev"
Dynamic: license-file
